MANIFEST.in
README
setup.py
ipv4ToLocation/__init__.py
ipv4ToLocation/ipv4ToLocation.py
ipv4ToLocation/ipv4wry.dat
ipv4ToLocation.py.egg-info/PKG-INFO
ipv4ToLocation.py.egg-info/SOURCES.txt
ipv4ToLocation.py.egg-info/dependency_links.txt
ipv4ToLocation.py.egg-info/top_level.txt