Metadata-Version: 1.1
Name: ipv4ToLocation.py
Version: 0.1.12
Summary: ipv4ToLocation
Home-page: https://github.com/nmghr9/getIPV4Location
Author: HouRong
Author-email: nmghr9@gmail.com
License: mit
Platform: any
Classifier: Development Status :: 4 - Beta
Classifier: Environment :: Plugins
Classifier: Intended Audience :: Developers
Classifier: License :: OSI Approved :: MIT License
Classifier: Operating System :: OS Independent
Classifier: Programming Language :: Python :: 3.4
Classifier: Topic :: Software Development :: Libraries :: Python Modules
